arenets/__init__.py
arenets/emb_converter.py
arenets/enum_input_types.py
arenets/enum_name_types.py
arenets/factory.py
arenets/labeling.py
arenets/sample.py
arenets/shapes.py
arenets/utils.py
arenets/arekit/__init__.py
arenets/arekit/common/__init__.py
arenets/arekit/common/data_type.py
arenets/arekit/common/utils.py
arenets/arekit/common/data/__init__.py
arenets/arekit/common/data/const.py
arenets/arekit/common/data/input/__init__.py
arenets/arekit/common/data/input/reader.py
arenets/arekit/common/data/input/sample.py
arenets/arekit/common/data/storages/__init__.py
arenets/arekit/common/data/storages/base.py
arenets/arekit/common/data/views/__init__.py
arenets/arekit/common/data/views/samples.py
arenets/arekit/common/experiment/__init__.py
arenets/arekit/common/experiment/api/__init__.py
arenets/arekit/common/experiment/api/base_samples_io.py
arenets/arekit/common/labels/__init__.py
arenets/arekit/common/labels/base.py
arenets/arekit/common/labels/scaler.py
arenets/arekit/common/pipeline/__init__.py
arenets/arekit/common/pipeline/base.py
arenets/arekit/common/pipeline/context.py
arenets/arekit/common/pipeline/items/__init__.py
arenets/arekit/common/pipeline/items/base.py
arenets/arekit/contrib/__init__.py
arenets/arekit/contrib/utils/__init__.py
arenets/arekit/contrib/utils/data/__init__.py
arenets/arekit/contrib/utils/data/readers/__init__.py
arenets/arekit/contrib/utils/data/readers/jsonl.py
arenets/arekit/contrib/utils/data/storages/__init__.py
arenets/arekit/contrib/utils/data/storages/jsonl_based.py
arenets/arekit/contrib/utils/io_utils/__init__.py
arenets/arekit/contrib/utils/io_utils/embedding.py
arenets/arekit/contrib/utils/io_utils/samples.py
arenets/arekit/contrib/utils/io_utils/utils.py
arenets/arekit/contrib/utils/np_utils/__init__.py
arenets/arekit/contrib/utils/np_utils/embedding.py
arenets/arekit/contrib/utils/np_utils/npz_utils.py
arenets/arekit/contrib/utils/np_utils/vocab.py
arenets/arekit/model/__init__.py
arenets/arekit/model/base.py
arenets-0.23.1.dist-info/LICENSE
arenets-0.23.1.dist-info/METADATA
arenets-0.23.1.dist-info/WHEEL
arenets-0.23.1.dist-info/top_level.txt
arenets-0.23.1.dist-info/RECORD
