Metadata-Version: 2.1
Name: arenets
Version: 0.23.1
Summary: Tensorflow-based framework which lists implementation of conventional neural network models (CNN, RNN-based) for Relation Extraction classification tasks as well as API for custom model implementation
Home-page: https://github.com/nicolay-r/AREnets
Author: Nicolay Rusnachenko
Author-email: rusnicolay@gmail.com
License: MIT License
Keywords: natural language processing,relation extraction,sentiment analysis
Platform: UNKNOWN
Classifier: Programming Language :: Python
Classifier: Programming Language :: Python :: 3.6
Classifier: Topic :: Software Development :: Libraries :: Python Modules
Classifier: Topic :: Scientific/Engineering :: Information Analysis
Requires-Python: >=3.6, <3.7
Requires-Dist: tensorflow-gpu (==1.14.0)
Requires-Dist: tqdm (==4.41.1)
